<?xml version="1.0"?>






































	<route>
		<id>612</id> 
		<rtpiFeedName></rtpiFeedName>
		<sn>612</sn> 
		<nm>612 Lwrnce-WWindsor-Prnceton Jct</nm> 
		<displayDesignator>612</displayDesignator> 
		<vmode>1</vmode>   
		
		<sbs>



		</sbs>

		<c>#009900</c>

		<pas>


			<pa>
				<id>248</id>

				<d>Lawrence Township</d> 
				<dd>Lawrence Township</dd>  
				<directionRtpiFeedName></directionRtpiFeedName>

				<pt>
					<lat>40.31567999999994</lat>
			        <lon>-74.62406999999916</lon>
			        <dtr>false</dtr> 

					<bs>
						<id>22932</id>
						<rtpiFeedName></rtpiFeedName>
						<st>ARRIVE PRINCETON JUNCTION</st> 
					</bs>

				</pt>

				<pt>
					<lat>40.31534</lat>
			        <lon>-74.62439</lon>
			        <dtr>false</dtr> 

				</pt>

				<pt>
					<lat>40.31481</lat>
			        <lon>-74.62424</lon>
			        <dtr>false</dtr> 

				</pt>

				<pt>
					<lat>40.31456</lat>
			        <lon>-74.62466</lon>
			        <dtr>false</dtr> 

				</pt>

				<pt>
					<lat>40.31335</lat>
			        <lon>-74.62613</lon>
			        <dtr>false</dtr> 

				</pt>

				<pt>
					<lat>40.31294</lat>
			        <lon>-74.62685</lon>
			        <dtr>false</dtr> 

				</pt>

				<pt>
					<lat>40.31191</lat>
			        <lon>-74.62828</lon>
			        <dtr>false</dtr> 

				</pt>

				<pt>
					<lat>40.30884</lat>
			        <lon>-74.63214</lon>
			        <dtr>false</dtr> 

				</pt>

				<pt>
					<lat>40.30853</lat>
			        <lon>-74.63249</lon>
			        <dtr>false</dtr> 

				</pt>

				<pt>
					<lat>40.30828</lat>
			        <lon>-74.63264</lon>
			        <dtr>false</dtr> 

				</pt>

				<pt>
					<lat>40.30801</lat>
			        <lon>-74.63265</lon>
			        <dtr>false</dtr> 

				</pt>

				<pt>
					<lat>40.30419</lat>
			        <lon>-74.63212</lon>
			        <dtr>false</dtr> 

				</pt>

				<pt>
					<lat>40.30418</lat>
			        <lon>-74.63228</lon>
			        <dtr>false</dtr> 

				</pt>

				<pt>
					<lat>40.30418</lat>
			        <lon>-74.63246</lon>
			        <dtr>false</dtr> 

				</pt>

				<pt>
					<lat>40.30412</lat>
			        <lon>-74.633</lon>
			        <dtr>false</dtr> 

				</pt>

				<pt>
					<lat>40.30395</lat>
			        <lon>-74.63368</lon>
			        <dtr>false</dtr> 

				</pt>

				<pt>
					<lat>40.30375</lat>
			        <lon>-74.63414</lon>
			        <dtr>false</dtr> 

				</pt>

				<pt>
					<lat>40.3035</lat>
			        <lon>-74.63457</lon>
			        <dtr>false</dtr> 

				</pt>

				<pt>
					<lat>40.3014</lat>
			        <lon>-74.63765</lon>
			        <dtr>false</dtr> 

				</pt>

				<pt>
					<lat>40.30038</lat>
			        <lon>-74.63934</lon>
			        <dtr>false</dtr> 

				</pt>

				<pt>
					<lat>40.29973</lat>
			        <lon>-74.64049</lon>
			        <dtr>false</dtr> 

				</pt>

				<pt>
					<lat>40.299657</lat>
			        <lon>-74.640705</lon>
			        <dtr>false</dtr> 

				</pt>

				<pt>
					<lat>40.299590000000315</lat>
			        <lon>-74.64090000000054</lon>
			        <dtr>false</dtr> 

					<bs>
						<id>30453</id>
						<rtpiFeedName></rtpiFeedName>
						<st>AVALON WATCH</st> 
					</bs>

				</pt>

				<pt>
					<lat>40.29937</lat>
			        <lon>-74.64113</lon>
			        <dtr>false</dtr> 

				</pt>

				<pt>
					<lat>40.29585</lat>
			        <lon>-74.64754</lon>
			        <dtr>false</dtr> 

				</pt>

				<pt>
					<lat>40.2957</lat>
			        <lon>-74.64784</lon>
			        <dtr>false</dtr> 

				</pt>

				<pt>
					<lat>40.2956</lat>
			        <lon>-74.64836</lon>
			        <dtr>false</dtr> 

				</pt>

				<pt>
					<lat>40.29567</lat>
			        <lon>-74.6487</lon>
			        <dtr>false</dtr> 

				</pt>

				<pt>
					<lat>40.29573</lat>
			        <lon>-74.64886</lon>
			        <dtr>false</dtr> 

				</pt>

				<pt>
					<lat>40.29648</lat>
			        <lon>-74.6499</lon>
			        <dtr>false</dtr> 

				</pt>

				<pt>
					<lat>40.2966</lat>
			        <lon>-74.65022</lon>
			        <dtr>false</dtr> 

				</pt>

				<pt>
					<lat>40.29662</lat>
			        <lon>-74.65058</lon>
			        <dtr>false</dtr> 

				</pt>

				<pt>
					<lat>40.29652</lat>
			        <lon>-74.65109</lon>
			        <dtr>false</dtr> 

				</pt>

				<pt>
					<lat>40.29585</lat>
			        <lon>-74.65345</lon>
			        <dtr>false</dtr> 

				</pt>

				<pt>
					<lat>40.295188</lat>
			        <lon>-74.656049</lon>
			        <dtr>false</dtr> 

				</pt>

				<pt>
					<lat>40.29514999999897</lat>
			        <lon>-74.65625999999864</lon>
			        <dtr>false</dtr> 

					<bs>
						<id>31862</id>
						<rtpiFeedName></rtpiFeedName>
						<st>CLARKSVILLE RD + RAVEN BLVD</st> 
					</bs>

				</pt>

				<pt>
					<lat>40.29501</lat>
			        <lon>-74.65657</lon>
			        <dtr>false</dtr> 

				</pt>

				<pt>
					<lat>40.29444</lat>
			        <lon>-74.65859</lon>
			        <dtr>false</dtr> 

				</pt>

				<pt>
					<lat>40.29346</lat>
			        <lon>-74.66307</lon>
			        <dtr>false</dtr> 

				</pt>

				<pt>
					<lat>40.29079</lat>
			        <lon>-74.674</lon>
			        <dtr>false</dtr> 

				</pt>

				<pt>
					<lat>40.29013</lat>
			        <lon>-74.67655</lon>
			        <dtr>false</dtr> 

				</pt>

				<pt>
					<lat>40.29164</lat>
			        <lon>-74.67734</lon>
			        <dtr>false</dtr> 

				</pt>

				<pt>
					<lat>40.29293</lat>
			        <lon>-74.67793</lon>
			        <dtr>false</dtr> 

				</pt>

				<pt>
					<lat>40.29346</lat>
			        <lon>-74.67811</lon>
			        <dtr>false</dtr> 

				</pt>

				<pt>
					<lat>40.29387</lat>
			        <lon>-74.67818</lon>
			        <dtr>false</dtr> 

				</pt>

				<pt>
					<lat>40.29593</lat>
			        <lon>-74.67823</lon>
			        <dtr>false</dtr> 

				</pt>

				<pt>
					<lat>40.29661</lat>
			        <lon>-74.67832</lon>
			        <dtr>false</dtr> 

				</pt>

				<pt>
					<lat>40.29727</lat>
			        <lon>-74.67857</lon>
			        <dtr>false</dtr> 

				</pt>

				<pt>
					<lat>40.29779</lat>
			        <lon>-74.67881</lon>
			        <dtr>false</dtr> 

				</pt>

				<pt>
					<lat>40.29816</lat>
			        <lon>-74.67903</lon>
			        <dtr>false</dtr> 

				</pt>

				<pt>
					<lat>40.29861</lat>
			        <lon>-74.67944</lon>
			        <dtr>false</dtr> 

				</pt>

				<pt>
					<lat>40.29902</lat>
			        <lon>-74.67992</lon>
			        <dtr>false</dtr> 

				</pt>

				<pt>
					<lat>40.30006</lat>
			        <lon>-74.68135</lon>
			        <dtr>false</dtr> 

				</pt>

				<pt>
					<lat>40.30058</lat>
			        <lon>-74.68193</lon>
			        <dtr>false</dtr> 

				</pt>

				<pt>
					<lat>40.30092</lat>
			        <lon>-74.68224</lon>
			        <dtr>false</dtr> 

				</pt>

				<pt>
					<lat>40.3019</lat>
			        <lon>-74.6829</lon>
			        <dtr>false</dtr> 

				</pt>

				<pt>
					<lat>40.30195</lat>
			        <lon>-74.68301</lon>
			        <dtr>false</dtr> 

				</pt>

				<pt>
					<lat>40.30173</lat>
			        <lon>-74.68346</lon>
			        <dtr>false</dtr> 

				</pt>

				<pt>
					<lat>40.30123</lat>
			        <lon>-74.68494</lon>
			        <dtr>false</dtr> 

				</pt>

				<pt>
					<lat>40.30118</lat>
			        <lon>-74.6851</lon>
			        <dtr>false</dtr> 

				</pt>

				<pt>
					<lat>40.30114</lat>
			        <lon>-74.68564</lon>
			        <dtr>false</dtr> 

				</pt>

				<pt>
					<lat>40.30116</lat>
			        <lon>-74.686</lon>
			        <dtr>false</dtr> 

				</pt>

				<pt>
					<lat>40.30134</lat>
			        <lon>-74.68683</lon>
			        <dtr>false</dtr> 

				</pt>

				<pt>
					<lat>40.30099</lat>
			        <lon>-74.68711</lon>
			        <dtr>false</dtr> 

				</pt>

				<pt>
					<lat>40.30089</lat>
			        <lon>-74.68723</lon>
			        <dtr>false</dtr> 

				</pt>

				<pt>
					<lat>40.30077</lat>
			        <lon>-74.68756</lon>
			        <dtr>false</dtr> 

				</pt>

				<pt>
					<lat>40.30067</lat>
			        <lon>-74.68757</lon>
			        <dtr>false</dtr> 

				</pt>

				<pt>
					<lat>40.29967</lat>
			        <lon>-74.687</lon>
			        <dtr>false</dtr> 

				</pt>

				<pt>
					<lat>40.29963</lat>
			        <lon>-74.68688</lon>
			        <dtr>false</dtr> 

				</pt>

				<pt>
					<lat>40.3002</lat>
			        <lon>-74.68505</lon>
			        <dtr>false</dtr> 

				</pt>

				<pt>
					<lat>40.30053</lat>
			        <lon>-74.68427</lon>
			        <dtr>false</dtr> 

				</pt>

				<pt>
					<lat>40.30064</lat>
			        <lon>-74.68421</lon>
			        <dtr>false</dtr> 

				</pt>

				<pt>
					<lat>40.300815</lat>
			        <lon>-74.684266</lon>
			        <dtr>false</dtr> 

				</pt>

				<pt>
					<lat>40.30094999999867</lat>
			        <lon>-74.68430999999845</lon>
			        <dtr>false</dtr> 

					<bs>
						<id>22455</id>
						<rtpiFeedName></rtpiFeedName>
						<st>YORKSHIRE MEADOWS</st> 
					</bs>

				</pt>

				<pt>
					<lat>40.30118</lat>
			        <lon>-74.6845</lon>
			        <dtr>false</dtr> 

				</pt>

				<pt>
					<lat>40.30126</lat>
			        <lon>-74.68444</lon>
			        <dtr>false</dtr> 

				</pt>

				<pt>
					<lat>40.30161</lat>
			        <lon>-74.68346</lon>
			        <dtr>false</dtr> 

				</pt>

				<pt>
					<lat>40.30159</lat>
			        <lon>-74.68311</lon>
			        <dtr>false</dtr> 

				</pt>

				<pt>
					<lat>40.30152</lat>
			        <lon>-74.68296</lon>
			        <dtr>false</dtr> 

				</pt>

				<pt>
					<lat>40.30131</lat>
			        <lon>-74.68272</lon>
			        <dtr>false</dtr> 

				</pt>

				<pt>
					<lat>40.30107</lat>
			        <lon>-74.68257</lon>
			        <dtr>false</dtr> 

				</pt>

				<pt>
					<lat>40.30072</lat>
			        <lon>-74.68227</lon>
			        <dtr>false</dtr> 

				</pt>

				<pt>
					<lat>40.30009</lat>
			        <lon>-74.68159</lon>
			        <dtr>false</dtr> 

				</pt>

				<pt>
					<lat>40.29959</lat>
			        <lon>-74.68096</lon>
			        <dtr>false</dtr> 

				</pt>

				<pt>
					<lat>40.29906</lat>
			        <lon>-74.68015</lon>
			        <dtr>false</dtr> 

				</pt>

				<pt>
					<lat>40.29876</lat>
			        <lon>-74.67978</lon>
			        <dtr>false</dtr> 

				</pt>

				<pt>
					<lat>40.29831</lat>
			        <lon>-74.67936</lon>
			        <dtr>false</dtr> 

				</pt>

				<pt>
					<lat>40.29795</lat>
			        <lon>-74.6791</lon>
			        <dtr>false</dtr> 

				</pt>

				<pt>
					<lat>40.29732</lat>
			        <lon>-74.67874</lon>
			        <dtr>false</dtr> 

				</pt>

				<pt>
					<lat>40.29693</lat>
			        <lon>-74.67858</lon>
			        <dtr>false</dtr> 

				</pt>

				<pt>
					<lat>40.29653</lat>
			        <lon>-74.67847</lon>
			        <dtr>false</dtr> 

				</pt>

				<pt>
					<lat>40.29571</lat>
			        <lon>-74.6784</lon>
			        <dtr>false</dtr> 

				</pt>

				<pt>
					<lat>40.29406</lat>
			        <lon>-74.67839</lon>
			        <dtr>false</dtr> 

				</pt>

				<pt>
					<lat>40.29338</lat>
			        <lon>-74.67825</lon>
			        <dtr>false</dtr> 

				</pt>

				<pt>
					<lat>40.29195</lat>
			        <lon>-74.67769</lon>
			        <dtr>false</dtr> 

				</pt>

				<pt>
					<lat>40.29175</lat>
			        <lon>-74.67836</lon>
			        <dtr>false</dtr> 

				</pt>

				<pt>
					<lat>40.29008</lat>
			        <lon>-74.67761</lon>
			        <dtr>false</dtr> 

				</pt>

				<pt>
					<lat>40.28996</lat>
			        <lon>-74.67768</lon>
			        <dtr>false</dtr> 

				</pt>

				<pt>
					<lat>40.28963</lat>
			        <lon>-74.67846</lon>
			        <dtr>false</dtr> 

				</pt>

				<pt>
					<lat>40.28892</lat>
			        <lon>-74.67978</lon>
			        <dtr>false</dtr> 

				</pt>

				<pt>
					<lat>40.28863</lat>
			        <lon>-74.68016</lon>
			        <dtr>false</dtr> 

				</pt>

				<pt>
					<lat>40.28837</lat>
			        <lon>-74.68058</lon>
			        <dtr>false</dtr> 

				</pt>

				<pt>
					<lat>40.2883</lat>
			        <lon>-74.68073</lon>
			        <dtr>false</dtr> 

				</pt>

				<pt>
					<lat>40.28824</lat>
			        <lon>-74.68126</lon>
			        <dtr>false</dtr> 

				</pt>

				<pt>
					<lat>40.28824</lat>
			        <lon>-74.68144</lon>
			        <dtr>false</dtr> 

				</pt>

				<pt>
					<lat>40.28822</lat>
			        <lon>-74.6818</lon>
			        <dtr>false</dtr> 

				</pt>

				<pt>
					<lat>40.28822</lat>
			        <lon>-74.68198</lon>
			        <dtr>false</dtr> 

				</pt>

				<pt>
					<lat>40.28821</lat>
			        <lon>-74.68215</lon>
			        <dtr>false</dtr> 

				</pt>

				<pt>
					<lat>40.28821</lat>
			        <lon>-74.68233</lon>
			        <dtr>false</dtr> 

				</pt>

				<pt>
					<lat>40.28819</lat>
			        <lon>-74.68269</lon>
			        <dtr>false</dtr> 

				</pt>

				<pt>
					<lat>40.28819</lat>
			        <lon>-74.68287</lon>
			        <dtr>false</dtr> 

				</pt>

				<pt>
					<lat>40.28818</lat>
			        <lon>-74.68305</lon>
			        <dtr>false</dtr> 

				</pt>

				<pt>
					<lat>40.28818</lat>
			        <lon>-74.68323</lon>
			        <dtr>false</dtr> 

				</pt>

				<pt>
					<lat>40.28817</lat>
			        <lon>-74.68341</lon>
			        <dtr>false</dtr> 

				</pt>

				<pt>
					<lat>40.28821</lat>
			        <lon>-74.68358</lon>
			        <dtr>false</dtr> 

				</pt>

				<pt>
					<lat>40.28837</lat>
			        <lon>-74.68387</lon>
			        <dtr>false</dtr> 

				</pt>

				<pt>
					<lat>40.28857</lat>
			        <lon>-74.68411</lon>
			        <dtr>false</dtr> 

				</pt>

				<pt>
					<lat>40.28832</lat>
			        <lon>-74.6845</lon>
			        <dtr>false</dtr> 

				</pt>

				<pt>
					<lat>40.28822</lat>
			        <lon>-74.68463</lon>
			        <dtr>false</dtr> 

				</pt>

				<pt>
					<lat>40.28798</lat>
			        <lon>-74.68478</lon>
			        <dtr>false</dtr> 

				</pt>

				<pt>
					<lat>40.28771</lat>
			        <lon>-74.68475</lon>
			        <dtr>false</dtr> 

				</pt>

				<pt>
					<lat>40.28706</lat>
			        <lon>-74.68445</lon>
			        <dtr>false</dtr> 

				</pt>

				<pt>
					<lat>40.28639</lat>
			        <lon>-74.68463</lon>
			        <dtr>false</dtr> 

				</pt>

				<pt>
					<lat>40.28633</lat>
			        <lon>-74.6843</lon>
			        <dtr>false</dtr> 

				</pt>

				<pt>
					<lat>40.2863</lat>
			        <lon>-74.68376</lon>
			        <dtr>false</dtr> 

				</pt>

				<pt>
					<lat>40.2864</lat>
			        <lon>-74.68306</lon>
			        <dtr>false</dtr> 

				</pt>

				<pt>
					<lat>40.28655</lat>
			        <lon>-74.68256</lon>
			        <dtr>false</dtr> 

				</pt>

				<pt>
					<lat>40.28676</lat>
			        <lon>-74.6821</lon>
			        <dtr>false</dtr> 

				</pt>

				<pt>
					<lat>40.28723</lat>
			        <lon>-74.68145</lon>
			        <dtr>false</dtr> 

				</pt>

				<pt>
					<lat>40.287444</lat>
			        <lon>-74.681071</lon>
			        <dtr>false</dtr> 

				</pt>

				<pt>
					<lat>40.28745000000024</lat>
			        <lon>-74.68106000000081</lon>
			        <dtr>false</dtr> 

					<bs>
						<id>22457</id>
						<rtpiFeedName></rtpiFeedName>
						<st>AVALON RUN</st> 
					</bs>

				</pt>

				<pt>
					<lat>40.2877</lat>
			        <lon>-74.6809</lon>
			        <dtr>false</dtr> 

				</pt>

				<pt>
					<lat>40.28842</lat>
			        <lon>-74.68006</lon>
			        <dtr>false</dtr> 

				</pt>

				<pt>
					<lat>40.28923</lat>
			        <lon>-74.67863</lon>
			        <dtr>false</dtr> 

				</pt>

				<pt>
					<lat>40.29005</lat>
			        <lon>-74.67677</lon>
			        <dtr>false</dtr> 

				</pt>

				<pt>
					<lat>40.28997</lat>
			        <lon>-74.67668</lon>
			        <dtr>false</dtr> 

				</pt>

				<pt>
					<lat>40.28668</lat>
			        <lon>-74.6749</lon>
			        <dtr>false</dtr> 

				</pt>

				<pt>
					<lat>40.28591</lat>
			        <lon>-74.67451</lon>
			        <dtr>false</dtr> 

				</pt>

				<pt>
					<lat>40.28564</lat>
			        <lon>-74.67453</lon>
			        <dtr>false</dtr> 

				</pt>

				<pt>
					<lat>40.28553</lat>
			        <lon>-74.67464</lon>
			        <dtr>false</dtr> 

				</pt>

				<pt>
					<lat>40.28482</lat>
			        <lon>-74.67697</lon>
			        <dtr>false</dtr> 

				</pt>

				<pt>
					<lat>40.284146</lat>
			        <lon>-74.676668</lon>
			        <dtr>false</dtr> 

				</pt>

				<pt>
					<lat>40.284040000000566</lat>
			        <lon>-74.67663000000097</lon>
			        <dtr>false</dtr> 

					<bs>
						<id>22458</id>
						<rtpiFeedName></rtpiFeedName>
						<st>AVALON RUN EAST</st> 
					</bs>

				</pt>

				<pt>
					<lat>40.2838</lat>
			        <lon>-74.67644</lon>
			        <dtr>false</dtr> 

				</pt>

				<pt>
					<lat>40.28329</lat>
			        <lon>-74.67618</lon>
			        <dtr>false</dtr> 

				</pt>

				<pt>
					<lat>40.28315</lat>
			        <lon>-74.67615</lon>
			        <dtr>false</dtr> 

				</pt>

				<pt>
					<lat>40.28251</lat>
			        <lon>-74.67642</lon>
			        <dtr>false</dtr> 

				</pt>

				<pt>
					<lat>40.28237</lat>
			        <lon>-74.67642</lon>
			        <dtr>false</dtr> 

				</pt>

				<pt>
					<lat>40.28148</lat>
			        <lon>-74.67596</lon>
			        <dtr>false</dtr> 

				</pt>

				<pt>
					<lat>40.27987</lat>
			        <lon>-74.67495</lon>
			        <dtr>false</dtr> 

				</pt>

				<pt>
					<lat>40.27962</lat>
			        <lon>-74.67482</lon>
			        <dtr>false</dtr> 

				</pt>

				<pt>
					<lat>40.279038</lat>
			        <lon>-74.674651</lon>
			        <dtr>false</dtr> 

				</pt>

				<pt>
					<lat>40.278860000000044</lat>
			        <lon>-74.67458000000052</lon>
			        <dtr>false</dtr> 

					<bs>
						<id>22459</id>
						<rtpiFeedName></rtpiFeedName>
						<st>AVALON RUN EAST II</st> 
					</bs>

				</pt>

				<pt>
					<lat>40.27808</lat>
			        <lon>-74.6739</lon>
			        <dtr>false</dtr> 

				</pt>

				<pt>
					<lat>40.27766</lat>
			        <lon>-74.67461</lon>
			        <dtr>false</dtr> 

				</pt>

				<pt>
					<lat>40.2771</lat>
			        <lon>-74.67584</lon>
			        <dtr>false</dtr> 

				</pt>

				<pt>
					<lat>40.27682</lat>
			        <lon>-74.67624</lon>
			        <dtr>false</dtr> 

				</pt>

				<pt>
					<lat>40.27482</lat>
			        <lon>-74.67813</lon>
			        <dtr>false</dtr> 

				</pt>

				<pt>
					<lat>40.27429</lat>
			        <lon>-74.6787</lon>
			        <dtr>false</dtr> 

				</pt>

				<pt>
					<lat>40.274107</lat>
			        <lon>-74.679042</lon>
			        <dtr>false</dtr> 

				</pt>

				<pt>
					<lat>40.27402000000059</lat>
			        <lon>-74.67923000000118</lon>
			        <dtr>false</dtr> 

					<bs>
						<id>22460</id>
						<rtpiFeedName></rtpiFeedName>
						<st>LIBERTY GREEN (GAZEBO BUS STOP)</st> 
					</bs>

				</pt>

				<pt>
					<lat>40.274262</lat>
			        <lon>-74.679579</lon>
			        <dtr>false</dtr> 

				</pt>

				<pt>
					<lat>40.27465</lat>
			        <lon>-74.67981</lon>
			        <dtr>false</dtr> 

				</pt>

				<pt>
					<lat>40.27463</lat>
			        <lon>-74.67997</lon>
			        <dtr>false</dtr> 

				</pt>

				<pt>
					<lat>40.27479</lat>
			        <lon>-74.68046</lon>
			        <dtr>false</dtr> 

				</pt>

				<pt>
					<lat>40.27468</lat>
			        <lon>-74.68052</lon>
			        <dtr>false</dtr> 

				</pt>

				<pt>
					<lat>40.27456</lat>
			        <lon>-74.68045</lon>
			        <dtr>false</dtr> 

				</pt>

				<pt>
					<lat>40.27455</lat>
			        <lon>-74.68028</lon>
			        <dtr>false</dtr> 

				</pt>

				<pt>
					<lat>40.27462</lat>
			        <lon>-74.68013</lon>
			        <dtr>false</dtr> 

				</pt>

				<pt>
					<lat>40.27462</lat>
			        <lon>-74.67996</lon>
			        <dtr>false</dtr> 

				</pt>

				<pt>
					<lat>40.27401</lat>
			        <lon>-74.67959</lon>
			        <dtr>false</dtr> 

				</pt>

				<pt>
					<lat>40.27422</lat>
			        <lon>-74.67881</lon>
			        <dtr>false</dtr> 

				</pt>

				<pt>
					<lat>40.27452</lat>
			        <lon>-74.67844</lon>
			        <dtr>false</dtr> 

				</pt>

				<pt>
					<lat>40.27674</lat>
			        <lon>-74.67632</lon>
			        <dtr>false</dtr> 

				</pt>

				<pt>
					<lat>40.27704</lat>
			        <lon>-74.67596</lon>
			        <dtr>false</dtr> 

				</pt>

				<pt>
					<lat>40.2776</lat>
			        <lon>-74.67473</lon>
			        <dtr>false</dtr> 

				</pt>

				<pt>
					<lat>40.27801</lat>
			        <lon>-74.67401</lon>
			        <dtr>false</dtr> 

				</pt>

				<pt>
					<lat>40.27819</lat>
			        <lon>-74.67374</lon>
			        <dtr>false</dtr> 

				</pt>

				<pt>
					<lat>40.2786</lat>
			        <lon>-74.67326</lon>
			        <dtr>false</dtr> 

				</pt>

				<pt>
					<lat>40.27905</lat>
			        <lon>-74.67285</lon>
			        <dtr>false</dtr> 

				</pt>

				<pt>
					<lat>40.28016</lat>
			        <lon>-74.67215</lon>
			        <dtr>false</dtr> 

				</pt>

				<pt>
					<lat>40.28032</lat>
			        <lon>-74.67186</lon>
			        <dtr>false</dtr> 

				</pt>

				<pt>
					<lat>40.28034</lat>
			        <lon>-74.67169</lon>
			        <dtr>false</dtr> 

				</pt>

				<pt>
					<lat>40.28029</lat>
			        <lon>-74.67153</lon>
			        <dtr>false</dtr> 

				</pt>

				<pt>
					<lat>40.28019</lat>
			        <lon>-74.67141</lon>
			        <dtr>false</dtr> 

				</pt>

				<pt>
					<lat>40.27969</lat>
			        <lon>-74.67111</lon>
			        <dtr>false</dtr> 

				</pt>

				<pt>
					<lat>40.27934</lat>
			        <lon>-74.67083</lon>
			        <dtr>false</dtr> 

				</pt>

				<pt>
					<lat>40.27782</lat>
			        <lon>-74.66999</lon>
			        <dtr>false</dtr> 

				</pt>

				<pt>
					<lat>40.27773</lat>
			        <lon>-74.67003</lon>
			        <dtr>false</dtr> 

				</pt>

				<pt>
					<lat>40.27704</lat>
			        <lon>-74.67198</lon>
			        <dtr>false</dtr> 

				</pt>

				<pt>
					<lat>40.27697</lat>
			        <lon>-74.67213</lon>
			        <dtr>false</dtr> 

				</pt>

				<pt>
					<lat>40.27686</lat>
			        <lon>-74.67223</lon>
			        <dtr>false</dtr> 

				</pt>

				<pt>
					<lat>40.27646</lat>
			        <lon>-74.67234</lon>
			        <dtr>false</dtr> 

				</pt>

				<pt>
					<lat>40.27609</lat>
			        <lon>-74.67257</lon>
			        <dtr>false</dtr> 

				</pt>

				<pt>
					<lat>40.27585</lat>
			        <lon>-74.67321</lon>
			        <dtr>false</dtr> 

				</pt>

				<pt>
					<lat>40.27496</lat>
			        <lon>-74.67502</lon>
			        <dtr>false</dtr> 

				</pt>

				<pt>
					<lat>40.27472</lat>
			        <lon>-74.67546</lon>
			        <dtr>false</dtr> 

				</pt>

				<pt>
					<lat>40.27451</lat>
			        <lon>-74.67568</lon>
			        <dtr>false</dtr> 

				</pt>

				<pt>
					<lat>40.27438</lat>
			        <lon>-74.67575</lon>
			        <dtr>false</dtr> 

				</pt>

				<pt>
					<lat>40.27411</lat>
			        <lon>-74.67578</lon>
			        <dtr>false</dtr> 

				</pt>

				<pt>
					<lat>40.27398</lat>
			        <lon>-74.67572</lon>
			        <dtr>false</dtr> 

				</pt>

				<pt>
					<lat>40.27316</lat>
			        <lon>-74.67477</lon>
			        <dtr>false</dtr> 

				</pt>

				<pt>
					<lat>40.27306</lat>
			        <lon>-74.67464</lon>
			        <dtr>false</dtr> 

				</pt>

				<pt>
					<lat>40.27284</lat>
			        <lon>-74.67399</lon>
			        <dtr>false</dtr> 

				</pt>

				<pt>
					<lat>40.272703</lat>
			        <lon>-74.673059</lon>
			        <dtr>false</dtr> 

				</pt>

				<pt>
					<lat>40.27268000000063</lat>
			        <lon>-74.67292000000079</lon>
			        <dtr>false</dtr> 

					<bs>
						<id>22463</id>
						<rtpiFeedName></rtpiFeedName>
						<st>LAWRENCE SQUARE</st> 
					</bs>

				</pt>

			</pa>


		</pas>
	</route>
